dc_stat_think/__init__.py
dc_stat_think/dc_stat_think.py
dc_stat_think/no_numba.py
dc_stat_think/original.py
dc_stat_think-1.1.1.dist-info/AUTHORS.rst
dc_stat_think-1.1.1.dist-info/LICENSE
dc_stat_think-1.1.1.dist-info/METADATA
dc_stat_think-1.1.1.dist-info/WHEEL
dc_stat_think-1.1.1.dist-info/top_level.txt
dc_stat_think-1.1.1.dist-info/RECORD
