Metadata-Version: 2.1
Name: dc-stat-think
Version: 1.1.1
Summary: Utility functions used in the DataCamp Statistical Thinking courses.
Home-page: https://github.com/justinbois/dc_stat_think
Author: Justin Bois
Author-email: bois@caltech.edu
License: MIT license
Keywords: dc_stat_think
Platform: UNKNOWN
Classifier: Development Status :: 4 - Beta
Classifier: Intended Audience :: Developers
Classifier: License :: OSI Approved :: MIT License
Classifier: Natural Language :: English
Classifier: Programming Language :: Python :: 3
Classifier: Programming Language :: Python :: 3.5
Classifier: Programming Language :: Python :: 3.6
Classifier: Programming Language :: Python :: 3.7
Classifier: Programming Language :: Python :: 3.8
